{"data":[{"id":"MDEwOlJlcG9zaXRvcnkxODI4MjA4MQ==","created_at":"2020-03-28T18:19:33Z","name":"ostent","description":"Ostent is a server tool to collect, display and report system metrics.","url":"https://github.com/ostrost/ostent","tags":[{"id":"1","name":"golang"},{"id":"12","name":"devops"},{"id":"111","name":"monitoring"}]},{"id":"MDEwOlJlcG9zaXRvcnk3NTg0NTQ4MQ==","created_at":"2020-03-28T18:19:33Z","name":"kickthemout","description":"💤 Kick devices off your network by performing an ARP Spoof attack.","url":"https://github.com/k4m4/kickthemout","tags":[{"id":"17","name":"python"},{"id":"22","name":"hacking"}]},{"id":"MDEwOlJlcG9zaXRvcnk3NjQ3NjcxNA==","created_at":"2020-03-28T18:19:33Z","name":"kubeplay","description":"kubeplay – a new way to interact with Kubernetes API from your terminal","url":"https://github.com/errordeveloper/kubeplay","tags":[{"id":"1","name":"golang"},{"id":"9","name":"kubernetes"},{"id":"53","name":"terminal"}]},{"id":"MDEwOlJlcG9zaXRvcnk3NzkzMDI3Mw==","created_at":"2020-03-28T18:19:33Z","name":"systemdlogger","description":"Exports systemd logs to an external service, eg cloudwatch, elasticsearch","url":"https://github.com/techjacker/systemdlogger","tags":[{"id":"17","name":"python"},{"id":"45","name":"logger"},{"id":"194","name":"systemd"}]},{"id":"MDEwOlJlcG9zaXRvcnk3NzQxOTM3Nw==","created_at":"2020-03-28T18:19:33Z","name":"ctop","description":"Top-like interface for container metrics","url":"https://github.com/bcicen/ctop","tags":[{"id":"1","name":"golang"},{"id":"11","name":"docker"}]},{"id":"MDEwOlJlcG9zaXRvcnk0Mjc5MzQyOA==","created_at":"2020-03-28T18:19:33Z","name":"flask-base","description":"A simple Flask boilerplate app with SQLAlchemy, Redis, User Authentication, and more.","url":"https://github.com/hack4impact/flask-base","tags":[{"id":"17","name":"python"},{"id":"32","name":"redis"},{"id":"77","name":"generator"},{"id":"195","name":"flask"}]},{"id":"MDEwOlJlcG9zaXRvcnkxNDA2NTY=","created_at":"2020-03-28T18:19:33Z","name":"tig","description":"Text-mode interface for git","url":"https://github.com/jonas/tig","tags":[{"id":"20","name":"c++"},{"id":"53","name":"terminal"},{"id":"130","name":"git"},{"id":"196","name":"ncurses"}]},{"id":"MDEwOlJlcG9zaXRvcnk4MDYwODc0Nw==","created_at":"2020-03-28T18:19:33Z","name":"mercure","description":"Mercure is a tool for security managers who want to train their colleague to phishing.","url":"https://github.com/atexio/mercure","tags":[{"id":"17","name":"python"},{"id":"41","name":"security"}]},{"id":"MDEwOlJlcG9zaXRvcnkyNjUwOTM2OQ==","created_at":"2020-03-28T18:19:33Z","name":"rkt","description":"[Project ended] rkt is a pod-native container engine for Linux. It is composable, secure, and built on standards.","url":"https://github.com/rkt/rkt","tags":null},{"id":"MDEwOlJlcG9zaXRvcnkzOTE5NzkyNQ==","created_at":"2020-03-28T18:19:33Z","name":"templates","description":"the default templates to use inside the fabric8 console ","url":"https://github.com/fabric8io/templates","tags":null}],"meta":{"page":50,"per_page":10,"total":1549}}