{"data":[{"id":"MDEwOlJlcG9zaXRvcnkzNjc4NzMx","created_at":"2020-03-28T18:19:30Z","name":"webpack","description":"A bundler for javascript and friends. Packs many modules into a few bundled assets. Code Splitting allows for loading parts of the application on demand. Through \"loaders\", modules can be CommonJs, AMD, ES6 modules, CSS, Images, JSON, Coffeescript, LESS, ... and your custom stuff.","url":"https://github.com/webpack/webpack","tags":null},{"id":"MDEwOlJlcG9zaXRvcnkzMjU0MzE4MQ==","created_at":"2020-03-28T18:19:30Z","name":"module-dependency","description":"Tool used to search for and visualise dependencies between Python modules","url":"https://github.com/DonaldWhyte/module-dependency","tags":null},{"id":"MDEwOlJlcG9zaXRvcnk1ODk2NDM3","created_at":"2020-03-28T18:19:30Z","name":"gobyexample","description":"Go by Example","url":"https://github.com/mmcgrana/gobyexample","tags":null},{"id":"MDEwOlJlcG9zaXRvcnk0MDQyMTgwNg==","created_at":"2020-03-28T18:19:30Z","name":"batavia","description":"A JavaScript implementation of the Python virtual machine.","url":"https://github.com/beeware/batavia","tags":null},{"id":"MDEwOlJlcG9zaXRvcnkyMzYxNjM5NA==","created_at":"2020-03-28T18:19:30Z","name":"profiling","description":"An interactive continuous Python profiler.","url":"https://github.com/what-studio/profiling","tags":null},{"id":"MDEwOlJlcG9zaXRvcnk4NjgxMjc=","created_at":"2020-03-28T18:19:30Z","name":"pyinotify","description":"Monitoring filesystems events with inotify on Linux.","url":"https://github.com/seb-m/pyinotify","tags":null},{"id":"MDEwOlJlcG9zaXRvcnk0MDcxNDQwMQ==","created_at":"2020-03-28T18:19:30Z","name":"termtile","description":"Terminal window manager for OS X","url":"https://github.com/apaszke/termtile","tags":null},{"id":"MDEwOlJlcG9zaXRvcnkzMDczMjM2NA==","created_at":"2020-03-28T18:19:30Z","name":"falcor","description":"A JavaScript library for efficient data fetching","url":"https://github.com/Netflix/falcor","tags":null},{"id":"MDEwOlJlcG9zaXRvcnkyODY3NzI3Mg==","created_at":"2020-03-28T18:19:30Z","name":"event-sourcing-examples","description":"Example code for my building and deploying microservices with event sourcing, CQRS and Docker presentation","url":"https://github.com/cer/event-sourcing-examples","tags":null},{"id":"MDEwOlJlcG9zaXRvcnk0MDc4OTg1Ng==","created_at":"2020-03-28T18:19:30Z","name":"shellscript-to-binary-converter","description":"Convert your shell scripts to binary files","url":"https://github.com/Utappia/shellscript-to-binary-converter","tags":null}],"meta":{"page":96,"per_page":10,"total":1549}}