{"data":[{"id":"MDEwOlJlcG9zaXRvcnkzNjgwNDQ4Ng==","created_at":"2020-03-28T18:19:31Z","name":"tqdm","description":"A Fast, Extensible Progress Bar for Python and CLI","url":"https://github.com/tqdm/tqdm","tags":null},{"id":"MDEwOlJlcG9zaXRvcnk0MzY4MTY3Nw==","created_at":"2020-03-28T18:19:31Z","name":"webtail","description":"Real time streaming of files in browser","url":"https://github.com/rparjun/webtail","tags":null},{"id":"MDEwOlJlcG9zaXRvcnkxOTIwNjM4NQ==","created_at":"2020-03-28T18:19:31Z","name":"skydns","description":"DNS service discovery for etcd","url":"https://github.com/skynetservices/skydns","tags":null},{"id":"MDEwOlJlcG9zaXRvcnk0NDIxMTQ2MQ==","created_at":"2020-03-28T18:19:31Z","name":"open-source-checklist","description":":octocat: A guide to help you remember important things when creating an open source project ;D","url":"https://github.com/afonsopacifer/open-source-checklist","tags":null},{"id":"MDEwOlJlcG9zaXRvcnkxNjU5OTAzMQ==","created_at":"2020-03-28T18:19:31Z","name":"jekyll-now","description":"Build a Jekyll blog in minutes, without touching the command line.","url":"https://github.com/barryclark/jekyll-now","tags":null},{"id":"MDEwOlJlcG9zaXRvcnkxMzQyMzg5MQ==","created_at":"2020-03-28T18:19:31Z","name":"json2html","description":"python module  for converting complex JSON object to HTML Table representation","url":"https://github.com/softvar/json2html","tags":null},{"id":"MDEwOlJlcG9zaXRvcnkzNzgyOTIzOA==","created_at":"2020-03-28T18:19:31Z","name":"Hack","description":"A typeface designed for source code","url":"https://github.com/source-foundry/Hack","tags":null},{"id":"MDEwOlJlcG9zaXRvcnkzNTk1NTY2Ng==","created_at":"2020-03-28T18:19:31Z","name":"the-art-of-command-line","description":"Master the command line, in one page","url":"https://github.com/jlevy/the-art-of-command-line","tags":null},{"id":"MDEwOlJlcG9zaXRvcnkxNDQ0MjYzNg==","created_at":"2020-03-28T18:19:31Z","name":"money","description":"Python money class with optional CLDR-backed locale-aware formatting and an extensible currency exchange solution.","url":"https://github.com/carlospalol/money","tags":null},{"id":"MDEwOlJlcG9zaXRvcnk0ODc3NDQzNA==","created_at":"2020-03-28T18:19:31Z","name":"osxlockdown","description":"[No longer maintained] Apple OS X tool to audit for, and remediate, security configuration settings.","url":"https://github.com/SummitRoute/osxlockdown","tags":null}],"meta":{"page":84,"per_page":10,"total":1613}}