{"data":[{"id":"MDEwOlJlcG9zaXRvcnkxMTg5NDUxMTg=","created_at":"2020-03-28T18:19:35Z","name":"fx","description":"Command-line tool and terminal JSON viewer 🔥","url":"https://github.com/antonmedv/fx","tags":[{"id":"53","name":"terminal"},{"id":"131","name":"json"}]},{"id":"MDEwOlJlcG9zaXRvcnkzMDcyNjI5","created_at":"2020-03-28T18:19:34Z","name":"jsonschema","description":"An(other) implementation of JSON Schema for Python","url":"https://github.com/Julian/jsonschema","tags":[{"id":"17","name":"python"},{"id":"131","name":"json"}]},{"id":"MDEwOlJlcG9zaXRvcnk1MTg0MDgwMg==","created_at":"2020-03-28T18:19:34Z","name":"pino","description":"🌲 super fast, all natural json logger 🌲","url":"https://github.com/pinojs/pino","tags":[{"id":"45","name":"logger"},{"id":"131","name":"json"},{"id":"136","name":"nodejs"}]},{"id":"MDEwOlJlcG9zaXRvcnkxMzUwNTUz","created_at":"2020-03-28T18:19:32Z","name":"gorgeous","description":"Convert between different data formats: JSON, XML, YAML, Ruby, email, URL-encoded","url":"https://github.com/mislav/gorgeous","tags":[{"id":"29","name":"utility"},{"id":"48","name":"csv"},{"id":"89","name":"ruby"},{"id":"131","name":"json"}]},{"id":"MDEwOlJlcG9zaXRvcnkxODkxODc0Ng==","created_at":"2020-03-28T18:19:32Z","name":"jmespath.js","description":"Javascript implementation of JMESPath, a query language for JSON","url":"https://github.com/jmespath/jmespath.js","tags":[{"id":"8","name":"javascript"},{"id":"131","name":"json"}]},{"id":"MDEwOlJlcG9zaXRvcnk4MzAwNzYz","created_at":"2020-03-28T18:19:32Z","name":"jmespath.py","description":"JMESPath is a query language for JSON.","url":"https://github.com/jmespath/jmespath.py","tags":[{"id":"8","name":"javascript"},{"id":"131","name":"json"}]}],"meta":{"page":1,"per_page":1543,"total":6}}