{"data":[{"id":"MDEwOlJlcG9zaXRvcnk2NzgzNDUwMg==","created_at":"2020-03-28T18:19:33Z","name":"mimesis","description":"Mimesis is a package for Python, which helps generate big volumes of fake data for a variety of purposes in a variety of languages. ","url":"https://github.com/lk-geimfari/mimesis","tags":[{"id":"17","name":"Python"},{"id":"193","name":"Fake"}]},{"id":"MDEwOlJlcG9zaXRvcnkzMzk5NDM4MA==","created_at":"2020-03-28T18:19:32Z","name":"go-fuzz","description":"Randomized testing for Go","url":"https://github.com/dvyukov/go-fuzz","tags":[{"id":"1","name":"Golang"},{"id":"47","name":"Testing"},{"id":"193","name":"Fake"}]},{"id":"MDEwOlJlcG9zaXRvcnk2NjYyMDc1","created_at":"2020-03-28T18:19:28Z","name":"faker","description":"Faker is a Python package that generates fake data for you.","url":"https://github.com/joke2k/faker","tags":[{"id":"17","name":"Python"},{"id":"47","name":"Testing"},{"id":"193","name":"Fake"}]}],"meta":{"page":1,"per_page":1598,"total":3}}