{"data":[{"id":"MDEwOlJlcG9zaXRvcnk5NTkwODQ=","created_at":"2020-03-28T18:19:30Z","name":"ShiftIt","description":"Managing windows size and position in OSX","url":"https://github.com/fikovnik/ShiftIt","tags":[{"id":"17","name":"Python"},{"id":"30","name":"MacOS"},{"id":"223","name":"Fabric"}]},{"id":"MDEwOlJlcG9zaXRvcnkyMzI1Nzkz","created_at":"2020-03-28T18:19:30Z","name":"fabtools","description":"Tools for writing awesome Fabric files","url":"https://github.com/fabtools/fabtools","tags":[{"id":"12","name":"DevOps"},{"id":"17","name":"Python"},{"id":"223","name":"Fabric"}]}],"meta":{"page":1,"per_page":1336,"total":2}}