{"data":[{"id":"MDEwOlJlcG9zaXRvcnkyOTk4Njc0OTk=","created_at":"2021-05-26T19:48:52Z","name":"rizin","description":"UNIX-like reverse engineering framework and command-line toolset.","url":"https://github.com/rizinorg/rizin","tags":[{"id":"282","name":"Binary"},{"id":"380","name":"Reverse Engineering"}]},{"id":"MDEwOlJlcG9zaXRvcnkxNjEwNDU1NzQ=","created_at":"2020-06-14T19:57:31Z","name":"min-sized-rust","description":"🦀 How to minimize Rust binary size 📦","url":"https://github.com/johnthagen/min-sized-rust","tags":[{"id":"13","name":"Rust"},{"id":"282","name":"Binary"},{"id":"283","name":"Compiler"}]}],"meta":{"page":1,"per_page":1784,"total":2}}