{"data":[{"id":"MDEwOlJlcG9zaXRvcnkzNDY4NzE1Mzg=","created_at":"2021-06-08T19:20:01Z","name":"wslg","description":"Enabling the Windows Subsystem for Linux to include support for Wayland and X server related scenarios","url":"https://github.com/microsoft/wslg","tags":[{"id":"44","name":"Windows"},{"id":"383","name":"WSL"}]},{"id":"MDEwOlJlcG9zaXRvcnkyODgyOTM5ODY=","created_at":"2021-05-26T19:48:52Z","name":"GWSL-Source","description":"The actual code for GWSL. And some prebuilt releases.","url":"https://github.com/Opticos/GWSL-Source","tags":[{"id":"44","name":"Windows"},{"id":"202","name":"SSH"},{"id":"260","name":"X11"},{"id":"383","name":"WSL"}]}],"meta":{"page":1,"per_page":1835,"total":2}}